cl_games/__init__.py
cl_games/collision.py
cl_games/game.py
cl_games/input.py
cl_games/sprites.py
cl_games-0.4.dist-info/LICENSE
cl_games-0.4.dist-info/METADATA
cl_games-0.4.dist-info/WHEEL
cl_games-0.4.dist-info/top_level.txt
cl_games-0.4.dist-info/RECORD
