Metadata-Version: 2.1
Name: cl-games
Version: 0.4
Summary: A package for creating video games for command line
Home-page: https://github.com/aaranyak/cl_games_V1-beta
Author: Aaranyak Ghosh
Author-email: aaranyak.ghosh@gmail.com
License: UNKNOWN
Project-URL: Bug Tracker, https://github.com/pypa/sampleproject/issues
Platform: UNKNOWN
Classifier: Programming Language :: Python :: 3
Classifier: License :: OSI Approved :: MIT License
Classifier: Operating System :: OS Independent
Requires-Python: >=3.6
License-File: LICENSE
Requires-Dist: pynput
